CHANGELOG.md
COPYING.txt
MANIFEST.in
README.rst
setup.py
rattail_dash/__init__.py
rattail_dash/_version.py
rattail_dash/commands.py
rattail_dash.egg-info/PKG-INFO
rattail_dash.egg-info/SOURCES.txt
rattail_dash.egg-info/dependency_links.txt
rattail_dash.egg-info/entry_points.txt
rattail_dash.egg-info/not-zip-safe
rattail_dash.egg-info/requires.txt
rattail_dash.egg-info/top_level.txt
rattail_dash/dashapp/__init__.py
rattail_dash/dashapp/base.py
rattail_dash/dashapp/sample.py